kandinsky/FAQ.md
kandinsky/README.md
kandinsky/__init__.py
kandinsky/__init__.pyi
kandinsky/__main__.py
kandinsky/util/3d_demo.py
kandinsky/util/core.py
kandinsky/util/demo.py
kandinsky/util/mac_patcher.py
kandinsky/util/data/app.ico
kandinsky/util/data/app.png
kandinsky/util/data/battery0.png
kandinsky/util/data/battery1.png
kandinsky/util/data/large_font.ttf
kandinsky/util/data/small_font.ttf
kandinsky/util/stuff/__init__.py
kandinsky/util/stuff/color.py
kandinsky/util/stuff/draw.py
kandinsky/util/stuff/gui.py
kandinsky/util/stuff/limiter.py
kandinsky/util/stuff/tests.py
kandinsky/util/stuff/vars.py
kandinsky-2.7.2.dist-info/METADATA
kandinsky-2.7.2.dist-info/WHEEL
kandinsky-2.7.2.dist-info/top_level.txt
kandinsky-2.7.2.dist-info/RECORD
