Metadata-Version: 2.1
Name: kandinsky
Version: 2.7.2
Summary: A small module allowing to link the kandinsky module, from the Numworks, to a window.
Home-page: https://github.com/ZetaMap/Kandinsky-Numworks
Author: ZetaMap
License: MIT
Project-URL: GitHub Project, https://github.com/ZetaMap/Kandinsky-Numworks
Project-URL: My GitHub Page, https://github.com/ZetaMap/
Classifier: Programming Language :: Python :: 3
Classifier: License :: OSI Approved :: MIT License
Classifier: Operating System :: Microsoft :: Windows
Classifier: Operating System :: Unix
Classifier: Operating System :: MacOS :: MacOS X
Requires-Python: >=3.6
Requires-Dist: pysdl2
Requires-Dist: pysdl2-dll
Requires-Dist: pyobjc-core ; sys_platform == "darwin"
Requires-Dist: pyobjc-framework-Cocoa ; sys_platform == "darwin"
